eda_ja/__init__.py
eda_ja/eda.py
eda_ja/file_utils.py
eda_ja/resources/__init__.py
eda_ja/resources/stop_words/__init__.py
eda_ja/resources/stop_words/en.txt
eda_ja/resources/stop_words/ja.txt
eda_ja-0.1.0.dist-info/WHEEL
eda_ja-0.1.0.dist-info/METADATA
eda_ja-0.1.0.dist-info/RECORD
