Metadata-Version: 2.1
Name: eda-ja
Version: 0.1.0
Summary: 
Author: Yuji Kamiya
Author-email: y.kamiya0@gmail.com
Requires-Python: >=3.7.1,<4.0.0
Classifier: Programming Language :: Python :: 3
Classifier: Programming Language :: Python :: 3.10
Classifier: Programming Language :: Python :: 3.8
Classifier: Programming Language :: Python :: 3.9
Requires-Dist: mecab-python3 (>=1.0.4,<2.0.0)
Requires-Dist: nltk (>=3.6.5,<4.0.0)
Requires-Dist: pandas (>=1.3.4,<2.0.0)
Requires-Dist: requests (>=2.26.0,<3.0.0)
Requires-Dist: tqdm (>=4.62.3,<5.0.0)
